src/__init__.py
src/cli.py
src/converter.py
src/gui.py
src/main.py
src/validation.py
tests/__init__.py
tests/conftest.py
tests/test_cli.py
tests/test_converter.py
tests/test_validation.py
comprehensive_base_converter-1.0.0.dist-info/LICENSE
comprehensive_base_converter-1.0.0.dist-info/METADATA
comprehensive_base_converter-1.0.0.dist-info/WHEEL
comprehensive_base_converter-1.0.0.dist-info/entry_points.txt
comprehensive_base_converter-1.0.0.dist-info/top_level.txt
comprehensive_base_converter-1.0.0.dist-info/RECORD
