Metadata-Version: 2.1
Name: comprehensive-base-converter
Version: 1.0.0
Summary: A comprehensive cross-platform base converter utility
Home-page: https://github.com/6639835/base-converter
Author: Base Converter Team
License: UNKNOWN
Platform: UNKNOWN
Classifier: Programming Language :: Python :: 3
Classifier: License :: OSI Approved :: MIT License
Classifier: Operating System :: OS Independent
Classifier: Development Status :: 5 - Production/Stable
Classifier: Intended Audience :: Developers
Classifier: Topic :: Utilities
Classifier: Topic :: Scientific/Engineering :: Mathematics
Requires-Python: >=3.7
License-File: LICENSE
